zylo_docs/__init__.py
zylo_docs/config.py
zylo_docs/integration.py
zylo_docs/logging.py
zylo_docs/middlewares/exception_handler.py
zylo_docs/routers/front_route.py
zylo_docs/routers/proxy_need_auth_route.py
zylo_docs/routers/proxy_route.py
zylo_docs/schemas/response.py
zylo_docs/schemas/schema_data.py
zylo_docs/security.py
zylo_docs/services/hub_server_service.py
zylo_docs/services/openapi_service.py
zylo_docs/services/user_server_service.py
zylo_docs/static/assets/index-Boq4V243.js
zylo_docs/static/assets/index-COibkS0S.css
zylo_docs/static/index.html
zylo_docs/utils/error_response.py
zylib_test-1.2.16.dist-info/METADATA
zylib_test-1.2.16.dist-info/WHEEL
zylib_test-1.2.16.dist-info/entry_points.txt
zylib_test-1.2.16.dist-info/RECORD
