Metadata-Version: 2.4
Name: zylib-test
Version: 1.2.16
Summary: Zylo-docs seamlessly integrates with FastAPI to automatically generate OpenAPI-compliant specs—so you can write your API docs faster and go home early.
Author: zylosystems
Author-email: engineering@zylosystems.com
Requires-Python: >=3.10
Classifier: Programming Language :: Python :: 3
Classifier: Programming Language :: Python :: 3.10
Classifier: Programming Language :: Python :: 3.11
Classifier: Programming Language :: Python :: 3.12
Classifier: Programming Language :: Python :: 3.13
Classifier: Programming Language :: Python :: 3.14
Requires-Dist: fastapi (>=0.70.0,<1)
Requires-Dist: httpx (>=0.25.0,<1)
Requires-Dist: uvicorn (>=0.15.0,<1)
